CHANGELOG.md
LICENSE
MANIFEST.in
README.md
setup.py
apply_defaults/__init__.py
apply_defaults/decorators.py
apply_defaults/py.typed
apply_defaults.egg-info/PKG-INFO
apply_defaults.egg-info/SOURCES.txt
apply_defaults.egg-info/dependency_links.txt
apply_defaults.egg-info/top_level.txt