Metadata-Version: 2.1
Name: apply-defaults
Version: 0.1.5
Summary: Apply values to optional params
Home-page: https://github.com/bcb/apply_defaults
Author: Beau Barker
License: UNKNOWN
Platform: UNKNOWN
License-File: LICENSE
